biblicus/__init__.py
biblicus/__main__.py
biblicus/cli.py
biblicus/constants.py
biblicus/context.py
biblicus/corpus.py
biblicus/crawl.py
biblicus/errors.py
biblicus/evaluation.py
biblicus/evidence_processing.py
biblicus/extraction.py
biblicus/extraction_evaluation.py
biblicus/frontmatter.py
biblicus/hook_logging.py
biblicus/hook_manager.py
biblicus/hooks.py
biblicus/ignore.py
biblicus/inference.py
biblicus/knowledge_base.py
biblicus/models.py
biblicus/retrieval.py
biblicus/sources.py
biblicus/time.py
biblicus/uris.py
biblicus/user_config.py
biblicus/_vendor/dotyaml/__init__.py
biblicus/_vendor/dotyaml/interpolation.py
biblicus/_vendor/dotyaml/loader.py
biblicus/_vendor/dotyaml/transformer.py
biblicus/analysis/__init__.py
biblicus/analysis/base.py
biblicus/analysis/llm.py
biblicus/analysis/models.py
biblicus/analysis/profiling.py
biblicus/analysis/schema.py
biblicus/analysis/topic_modeling.py
biblicus/backends/__init__.py
biblicus/backends/base.py
biblicus/backends/hybrid.py
biblicus/backends/scan.py
biblicus/backends/sqlite_full_text_search.py
biblicus/backends/vector.py
biblicus/extractors/__init__.py
biblicus/extractors/base.py
biblicus/extractors/deepgram_stt.py
biblicus/extractors/docling_granite_text.py
biblicus/extractors/docling_smol_text.py
biblicus/extractors/markitdown_text.py
biblicus/extractors/metadata_text.py
biblicus/extractors/openai_stt.py
biblicus/extractors/paddleocr_vl_text.py
biblicus/extractors/pass_through_text.py
biblicus/extractors/pdf_text.py
biblicus/extractors/pipeline.py
biblicus/extractors/rapidocr_text.py
biblicus/extractors/select_longest_text.py
biblicus/extractors/select_override.py
biblicus/extractors/select_smart_override.py
biblicus/extractors/select_text.py
biblicus/extractors/unstructured_text.py
biblicus-0.14.0.dist-info/licenses/LICENSE
biblicus-0.14.0.dist-info/METADATA
biblicus-0.14.0.dist-info/WHEEL
biblicus-0.14.0.dist-info/entry_points.txt
biblicus-0.14.0.dist-info/top_level.txt
biblicus-0.14.0.dist-info/RECORD
