Metadata-Version: 2.4
Name: biblicus
Version: 0.14.0
Summary: Command line interface and Python library for corpus ingestion, retrieval, and evaluation.
License: MIT
Requires-Python: >=3.9
License-File: LICENSE
Requires-Dist: pydantic>=2.0
Requires-Dist: PyYAML>=6.0
Requires-Dist: pypdf>=4.0
Provides-Extra: dev
Requires-Dist: behave>=1.2.6; extra == "dev"
Requires-Dist: coverage[toml]>=7.0; extra == "dev"
Requires-Dist: sphinx>=7.0; extra == "dev"
Requires-Dist: myst-parser>=2.0; extra == "dev"
Requires-Dist: sphinx_rtd_theme>=2.0; extra == "dev"
Requires-Dist: ruff>=0.4.0; extra == "dev"
Requires-Dist: black>=24.0; extra == "dev"
Requires-Dist: python-semantic-release>=9.0.0; extra == "dev"
Provides-Extra: openai
Requires-Dist: openai>=1.0; extra == "openai"
Provides-Extra: unstructured
Requires-Dist: unstructured>=0.12.0; extra == "unstructured"
Requires-Dist: python-docx>=1.1.0; extra == "unstructured"
Provides-Extra: ocr
Requires-Dist: rapidocr-onnxruntime>=1.3.0; extra == "ocr"
Provides-Extra: paddleocr
Requires-Dist: paddleocr>=2.7.0; extra == "paddleocr"
Requires-Dist: paddlepaddle>=2.5.0; extra == "paddleocr"
Requires-Dist: huggingface_hub>=0.20.0; extra == "paddleocr"
Requires-Dist: requests>=2.28.0; extra == "paddleocr"
Provides-Extra: markitdown
Requires-Dist: markitdown[all]>=0.1.0; python_version >= "3.10" and extra == "markitdown"
Provides-Extra: deepgram
Requires-Dist: deepgram-sdk>=3.0; extra == "deepgram"
Provides-Extra: docling
Requires-Dist: docling[vlm]>=2.0.0; extra == "docling"
Provides-Extra: docling-mlx
Requires-Dist: docling[mlx-vlm]>=2.0.0; extra == "docling-mlx"
Provides-Extra: topic-modeling
Requires-Dist: bertopic>=0.15.0; extra == "topic-modeling"
Provides-Extra: datasets
Requires-Dist: datasets>=2.18.0; extra == "datasets"
Dynamic: license-file
